<ns0:DataModelInfo xmlns:ns0="http://schemas.qualisystems.com/ResourceManagement/DataModelSchema.xsd">
	<ns0:ResourceFamilies>
	</ns0:ResourceFamilies>
  <ns0:ScriptDescriptors>
    <ns0:ScriptDescriptor Alias="Setup script" CategoryName="Hidden Commands" Name="Default Sandbox Setup 3.0" Version="3.5.0">
      <ns0:ScriptInputs />
    </ns0:ScriptDescriptor>
    <ns0:ScriptDescriptor Alias="Teardown script" CategoryName="Hidden Commands" Name="Default Sandbox Teardown 3.0" Version="3.5.0">
      <ns0:ScriptInputs />
    </ns0:ScriptDescriptor>
      <ns0:ScriptDescriptor Alias="Save script" CategoryName="Hidden Commands" Name="Default Sandbox Save 3.0" Version="3.5.0">
      <ns0:ScriptInputs />
    </ns0:ScriptDescriptor>
    <ns0:ScriptDescriptor Alias="Restore script" CategoryName="Hidden Commands" Name="Default Sandbox Restore 3.0" Version="3.5.0">
      <ns0:ScriptInputs />
    </ns0:ScriptDescriptor>
  </ns0:ScriptDescriptors>
</ns0:DataModelInfo>